blockify/__init__.py
blockify/algorithms.py
blockify/annotation.py
blockify/downsampling.py
blockify/normalization.py
blockify/parsers.py
blockify/segmentation.py
blockify/utilities.py
blockify-0.2.2.data/scripts/blockify
blockify-0.2.2.dist-info/LICENSE.rst
blockify-0.2.2.dist-info/METADATA
blockify-0.2.2.dist-info/WHEEL
blockify-0.2.2.dist-info/top_level.txt
blockify-0.2.2.dist-info/RECORD
